peon/__init__.py
peon/predict.py
peon/train.py
peon_gui/gui.py
pollencount-0.0.7.dist-info/licenses/LICENSE
pollencount-0.0.7.dist-info/METADATA
pollencount-0.0.7.dist-info/WHEEL
pollencount-0.0.7.dist-info/entry_points.txt
pollencount-0.0.7.dist-info/top_level.txt
pollencount-0.0.7.dist-info/RECORD
