Metadata-Version: 2.4
Name: PollEncOuNt
Version: 0.0.7
Summary: The purpose of this project is to count the number of alive and dead pollens in an image.
Author-email: Shan-En Chen <shawn.for.office@gmail.com>
Classifier: Programming Language :: Python :: 3
Classifier: License :: OSI Approved :: MIT License
Classifier: Operating System :: OS Independent
Requires-Python: >=3.11
License-File: LICENSE
Requires-Dist: pandas
Requires-Dist: ultralytics>=8.3.67
Dynamic: license-file
